optimo/__init__.py
optimo/api.py
optimo/base.py
optimo/errors.py
optimo/models.py
optimo/util.py
optimo-0.2.3.dist-info/DESCRIPTION.rst
optimo-0.2.3.dist-info/METADATA
optimo-0.2.3.dist-info/RECORD
optimo-0.2.3.dist-info/WHEEL
optimo-0.2.3.dist-info/metadata.json
optimo-0.2.3.dist-info/top_level.txt
tests/__init__.py
tests/conftest.py
tests/test_encoders.py
tests/test_models.py
tests/test_optimoapi.py
tests/util.py
