Metadata-Version: 2.0
Name: optimo
Version: 0.2.3
Summary: A python library for OptimoRoute's web service
Home-page: https://github.com/fieldaware/optimoroute
Author: George Spanos
Author-email: spanosgeorge@gmail.com
License: BSD
Platform: UNKNOWN
Classifier: Development Status :: 4 - Beta
Classifier: Intended Audience :: Developers
Classifier: License :: OSI Approved :: BSD License
Classifier: Natural Language :: English
Classifier: Programming Language :: Python
Classifier: Programming Language :: Python :: 2.7
Requires-Dist: requests
Requires-Dist: pytz
